{"project_name": "zpp-mim-1920", "bucket_name": "zpp-bucket-1920", "config_dump": "config_dump.json", "gcp_model_dir": "bert-bucket-golkarolka/bert_model3", "voc_size": 2000, "train_steps": 1000000, "train_batch_size": 128, "bert_folder": "bert", "vocab_filename": "vocab.txt", "executable": "pretrain_bert/bert_runner.py", "tpu_name": "bert3", "model_dir": "bert_model", "tpu_cores": 8, "zone": "us-central1-f", "eval_batch_size": 64, "max_predictions": 80, "pretraining_dir": "bert-bucket-golkarolka/pretrain_data3", "session_name": "3", "masked_lm_prob": 0.8, "max_seq_length": 512, "bert_config_filename": "bert_config.json", "vocab_thms_ls": "vocab_thms_ls.txt", "checkpoints_steps": 2500}